novelai_api/BanList.py
novelai_api/BiasGroup.py
novelai_api/DirectorToolsPreset.py
novelai_api/GlobalSettings.py
novelai_api/Idstore.py
novelai_api/ImagePreset.py
novelai_api/ImagePreset_CostTables.py
novelai_api/Keystore.py
novelai_api/Msgpackr_Extensions.py
novelai_api/NovelAIError.py
novelai_api/NovelAI_API.py
novelai_api/Preset.py
novelai_api/SchemaValidator.py
novelai_api/StoryHandler.py
novelai_api/Tokenizer.py
novelai_api/__init__.py
novelai_api/__main__.py
novelai_api/_high_level.py
novelai_api/_low_level.py
novelai_api/image_presets/presets_v1/default.preset
novelai_api/image_presets/presets_v2/default.preset
novelai_api/image_presets/presets_v3/default.preset
novelai_api/image_presets/presets_v3/default_furry.preset
novelai_api/image_presets/presets_v4/default.preset
novelai_api/image_presets/presets_v45/default.preset
novelai_api/poetry_scripts.py
novelai_api/presets/presets_2.7B/Storywriter.preset
novelai_api/presets/presets_2.7B/default.txt
novelai_api/presets/presets_6B_v4/Best Guess.preset
novelai_api/presets/presets_6B_v4/Coherent Creativity.preset
novelai_api/presets/presets_6B_v4/Emperor Moth.preset
novelai_api/presets/presets_6B_v4/Luna Moth.preset
novelai_api/presets/presets_6B_v4/Pleasing Results.preset
novelai_api/presets/presets_6B_v4/Sphinx Moth.preset
novelai_api/presets/presets_6B_v4/Storywriter.preset
novelai_api/presets/presets_6B_v4/default.txt
novelai_api/presets/presets_clio_v1/Amber Zippo.preset
novelai_api/presets/presets_clio_v1/Blended Coffee.preset
novelai_api/presets/presets_clio_v1/Edgewise CFG.preset
novelai_api/presets/presets_clio_v1/Edgewise.preset
novelai_api/presets/presets_clio_v1/Flat-Out.preset
novelai_api/presets/presets_clio_v1/Fresh Coffee.preset
novelai_api/presets/presets_clio_v1/Long Press.preset
novelai_api/presets/presets_clio_v1/Talker C.preset
novelai_api/presets/presets_clio_v1/Vingt-Un.preset
novelai_api/presets/presets_clio_v1/default.txt
novelai_api/presets/presets_euterpe_v2/Ace of Spades.preset
novelai_api-0.34.1.dist-info/LICENSE
novelai_api-0.34.1.dist-info/METADATA
novelai_api-0.34.1.dist-info/WHEEL
novelai_api-0.34.1.dist-info/entry_points.txt
novelai_api-0.34.1.dist-info/RECORD
