Metadata-Version: 2.3
Name: novelai-api
Version: 0.34.1
Summary: Python API for the NovelAI REST API
License: MIT
Keywords: python,NovelAI,NAI,API
Author: Aedial
Author-email: aedial.dev@gmail.com
Requires-Python: >=3.8.10,<4.0.0
Classifier: Development Status :: 3 - Alpha
Classifier: Intended Audience :: Developers
Classifier: License :: OSI Approved :: MIT License
Classifier: Operating System :: OS Independent
Classifier: Programming Language :: Python :: 3
Classifier: Programming Language :: Python :: 3.9
Classifier: Programming Language :: Python :: 3.10
Classifier: Programming Language :: Python :: 3.11
Classifier: Programming Language :: Python :: 3.12
Classifier: Programming Language :: Python :: 3.13
Classifier: Programming Language :: Python :: 3.8
Requires-Dist: PyNaCl (>=1.5.0,<2.0.0)
Requires-Dist: aiohttp[speedups] (>=3.9.3,<4.0.0)
Requires-Dist: argon2-cffi (>=23.1.0,<24.0.0)
Requires-Dist: ftfy (>=6.1.3,<7.0.0)
Requires-Dist: jsonschema (>=4.21.1,<5.0.0)
Requires-Dist: msgpackr-python (>=0.1.2,<0.2.0)
Requires-Dist: pillow (>=10.4.0,<11.0.0)
Requires-Dist: poetry (>=1.8.5,<2.0.0)
Requires-Dist: regex (>=2023.12.25,<2024.0.0)
Requires-Dist: sentencepiece (>=0.2.0,<0.3.0)
Requires-Dist: tokenizers (>=0.15.1,<0.16.0)
Project-URL: Bug Tracker, https://github.com/Aedial/novelai-api/issues
Project-URL: Repository, https://github.com/Aedial/novelai-api
